omnistat/__init__.py
omnistat/api/__init__.py
omnistat/api/dependencies.py
omnistat/api/main.py
omnistat/api/routes/__init__.py
omnistat/api/routes/analysis_routes.py
omnistat/api/routes/data_routes.py
omnistat/cli/__init__.py
omnistat/cli/commands/__init__.py
omnistat/cli/commands/analyze.py
omnistat/cli/commands/data.py
omnistat/cli/helpers.py
omnistat/cli/main.py
omnistat/core/__init__.py
omnistat/core/analysis.py
omnistat/core/config.py
omnistat/core/data_loader.py
omnistat/core/data_storage.py
omnistat/core/preprocess.py
omnistat/core/utils.py
omnistat/core/visualization.py
omnistat/data/__init__.py
omnistat/data/config.json
omnistat/data/database.db
omnistat/data/dataset_1.h5
omnistat/extensions/__init__.py
omnistat/extensions/custom_analyzers.py
omnistat/extensions/custom_loaders.py
omnistat/extensions/custom_visualizers.py
omnistat/extensions/third_party_tools/__init__.py
omnistat/extensions/third_party_tools/third_party_integration.py
omnistat/main.py
omnistat/pipelines/__init__.py
omnistat/pipelines/pipeline_manager.py
omnistat/pipelines/proteomics_pipeline.py
omnistat/pipelines/sc_pipeline.py
omnistat/pipelines/transcript_pipeline.py
omnistat/plugins/__init__.py
omnistat/plugins/example_plugin.py
omnistat/plugins/plugin_manager.py
omnistat/workflows/__init__.py
omnistat/workflows/proteomics/__init__.py
omnistat/workflows/proteomics/proteomics_analysis.py
omnistat/workflows/proteomics/proteomics_preprocess.py
omnistat/workflows/proteomics/proteomics_visualization.py
omnistat/workflows/single_cell/__init__.py
omnistat/workflows/single_cell/sc_analysis.py
omnistat/workflows/single_cell/sc_preprocess.py
omnistat/workflows/single_cell/sc_visualization.py
omnistat/workflows/transcriptomics/__init__.py
omnistat/workflows/transcriptomics/transcript_analysis.py
omnistat/workflows/transcriptomics/transcript_preprocess.py
omnistat/workflows/transcriptomics/transcript_visualization.py
omnistat-0.1.0.dist-info/METADATA
omnistat-0.1.0.dist-info/WHEEL
omnistat-0.1.0.dist-info/RECORD
