Metadata-Version: 2.1
Name: omnistat
Version: 0.1.0
Summary: 
Author: younthing
Author-email: fanxingfu3344@gmail.com
Requires-Python: >=3.11,<4.0
Classifier: Programming Language :: Python :: 3
Classifier: Programming Language :: Python :: 3.11
Classifier: Programming Language :: Python :: 3.12
Requires-Dist: fastapi (>=0.112.0,<0.113.0)
Requires-Dist: matplotlib (>=3.9.2,<4.0.0)
Requires-Dist: pandas (>=2.2.2,<3.0.0)
Requires-Dist: scanpy (>=1.10.2,<2.0.0)
Requires-Dist: scikit-learn (>=1.5.1,<2.0.0)
Requires-Dist: typer (>=0.12.3,<0.13.0)
